biometatools/__init__.py
biometatools/coords_on_meta_feat.py
biometatools/rel_pos_bam_vs_bed.py
biometatools-1.1.1.dist-info/LICENSE
biometatools-1.1.1.dist-info/METADATA
biometatools-1.1.1.dist-info/WHEEL
biometatools-1.1.1.dist-info/entry_points.txt
biometatools-1.1.1.dist-info/top_level.txt
biometatools-1.1.1.dist-info/RECORD
