Metadata-Version: 2.1
Name: biometatools
Version: 1.1.1
Summary: Package for meta-analysis of reads compared to features
Home-page: https://github.com/maragkakislab/biometatools
Author: MaragkakisLab
Author-email: emmanouil.maragkakis@nih.gov
Project-URL: Bug Tracker, https://github.com/maragkakislab/biometatools/issues
Classifier: Programming Language :: Python :: 3
Classifier: License :: Public Domain
Classifier: Operating System :: OS Independent
Requires-Python: >=3.4
License-File: LICENSE
Requires-Dist: pandas
Requires-Dist: pysam
Requires-Dist: matplotlib
Requires-Dist: seaborn
